prophetverse/__init__.py
prophetverse/_model.py
prophetverse/budget_optimization/__init__.py
prophetverse/budget_optimization/base.py
prophetverse/budget_optimization/constraints.py
prophetverse/budget_optimization/objectives.py
prophetverse/budget_optimization/optimizer.py
prophetverse/budget_optimization/parametrization_transformations.py
prophetverse/datasets/__init__.py
prophetverse/datasets/_mmm/dataset1.py
prophetverse/datasets/_mmm/dataset1_panel.py
prophetverse/datasets/_mmm/dataset1_panel_posterior_samples.json
prophetverse/datasets/_mmm/dataset1_posterior_samples.json
prophetverse/datasets/_mmm/dataset2_branding.py
prophetverse/datasets/_mmm/dataset2_branding_posterior_samples.json
prophetverse/datasets/loaders.py
prophetverse/datasets/raw/tensorflow_tensorflow-stars-history.csv
prophetverse/datasets/raw/tourism.csv
prophetverse/datasets/synthetic/__init__.py
prophetverse/datasets/synthetic/_composite_effect_example.py
prophetverse/datasets/synthetic/_squared_exogenous.py
prophetverse/distributions/__init__.py
prophetverse/distributions/_inverse_functions.py
prophetverse/distributions/hurdle_distribution.py
prophetverse/distributions/reparametrization.py
prophetverse/distributions/truncated_discrete.py
prophetverse/effects/__init__.py
prophetverse/effects/adstock.py
prophetverse/effects/base.py
prophetverse/effects/chain.py
prophetverse/effects/constant.py
prophetverse/effects/exact_likelihood.py
prophetverse/effects/forward.py
prophetverse/effects/fourier.py
prophetverse/effects/hill.py
prophetverse/effects/ignore_input.py
prophetverse/effects/lift_likelihood.py
prophetverse/effects/linear.py
prophetverse/effects/log.py
prophetverse/effects/michaelis_menten.py
prophetverse/effects/operations.py
prophetverse/effects/proxy_likelihood.py
prophetverse/effects/target/__init__.py
prophetverse/effects/target/base.py
prophetverse/effects/target/hurdle.py
prophetverse/effects/target/multivariate.py
prophetverse/effects/target/univariate.py
prophetverse-0.10.0.dist-info/METADATA
prophetverse-0.10.0.dist-info/WHEEL
prophetverse-0.10.0.dist-info/licenses/LICENSE
prophetverse-0.10.0.dist-info/RECORD
