Metadata-Version: 2.4
Name: prophetverse
Version: 0.10.0
Summary: A multiverse of prophet models, for forecasting and Marketing Mix Modeling.
License-File: LICENSE
Author: Felipe Angelim
Author-email: felipeangelim@gmail.com
Requires-Python: >=3.9,<3.13
Classifier: Programming Language :: Python :: 3
Classifier: Programming Language :: Python :: 3.9
Classifier: Programming Language :: Python :: 3.10
Classifier: Programming Language :: Python :: 3.11
Classifier: Programming Language :: Python :: 3.12
Provides-Extra: dev
Requires-Dist: black (>=24.4.2,<26.0.0) ; extra == "dev"
Requires-Dist: commitlint (>=1.0.0,<2.0.0) ; extra == "dev"
Requires-Dist: graphviz (>=0.20.3,<0.22.0)
Requires-Dist: ipykernel (>=6.26.0,<7.0.0) ; extra == "dev"
Requires-Dist: isort (>=5.13.2,<7.0.0) ; extra == "dev"
Requires-Dist: jupyterlab (>=4.4.2,<5.0.0) ; extra == "dev"
Requires-Dist: matplotlib (>=3.8.2,<4.0.0) ; extra == "dev"
Requires-Dist: mypy (>=1.10.0,<2.0.0) ; extra == "dev"
Requires-Dist: numpyro (>=0.19.0)
Requires-Dist: optax (>=0.2.4)
Requires-Dist: pre-commit (>=3.7.1,<5.0.0) ; extra == "dev"
Requires-Dist: pydocstyle (>=6.3.0,<7.0.0) ; extra == "dev"
Requires-Dist: pylint (>=3.2.2,<4.0.0) ; extra == "dev"
Requires-Dist: pytest (>=8.0.0,<9.0.0) ; extra == "dev"
Requires-Dist: pytest-cov (>=5.0.0,<8.0.0) ; extra == "dev"
Requires-Dist: pyyaml (>=6.0.2,<7.0.0) ; extra == "dev"
Requires-Dist: quartodoc (>=0.9.1,<0.12.0) ; extra == "dev"
Requires-Dist: scikit-base (>=0.12.0,<0.13.0)
Requires-Dist: seaborn (>=0.13.2,<0.14.0) ; extra == "dev"
Requires-Dist: skpro (>=2.9.2,<3.0.0)
Requires-Dist: sktime (>=0.30.0)
Requires-Dist: statsmodels (>=0.14.4,<0.15.0) ; extra == "dev"
